<?xml version="1.0" encoding="utf-8" ?>
<c2layout>
    <name>Menu Principal</name>
    <sid>366175455085962</sid>
    <event-sheet>Eventos Menu Principal</event-sheet>
    <size>
        <width>800</width>
        <height>400</height>
    </size>
    <margins>
        <horizontal>800</horizontal>
        <vertical>400</vertical>
    </margins>
    <unbounded-scrolling>0</unbounded-scrolling>
    <layers>
        <layer name="Layer 0" sid="476382373102528">
            <initially-visible>1</initially-visible>
            <background-color>255,255,255</background-color>
            <transparent>0</transparent>
            <parallax>
                <x>1</x>
                <y>1</y>
            </parallax>
            <zoom-rate>1</zoom-rate>
            <opacity>1</opacity>
            <force-own-texture>0</force-own-texture>
            <global>0</global>
            <use-render-cells>0</use-render-cells>
            <blend-mode>0</blend-mode>
            <effect-fallback>0</effect-fallback>
            <instances>
                <instance type="asfalto1" uid="2901">
                    <properties>
                        <initial-visibility>Visible</initial-visibility>
                        <hotspot>Top-left</hotspot>
                    </properties>
                    <blend-mode>0</blend-mode>
                    <effect-fallback>0</effect-fallback>
                    <world>
                        <x>0</x>
                        <y>0</y>
                        <z>0</z>
                        <width>800</width>
                        <height>416</height>
                        <depth>0</depth>
                        <hotspotX>0</hotspotX>
                        <hotspotY>0</hotspotY>
                        <angle>0</angle>
                        <opacity>1</opacity>
                    </world>
                </instance>
                <instance type="marcaVaga1" uid="2969">
                    <properties>
                        <initial-visibility>Visible</initial-visibility>
                        <hotspot>Top-left</hotspot>
                    </properties>
                    <blend-mode>0</blend-mode>
                    <effect-fallback>0</effect-fallback>
                    <world>
                        <x>794.46673584</x>
                        <y>398.740478516</y>
                        <z>0</z>
                        <width>427.185089111</width>
                        <height>6</height>
                        <depth>0</depth>
                        <hotspotX>0</hotspotX>
                        <hotspotY>0</hotspotY>
                        <angle>-1.57079649</angle>
                        <opacity>1</opacity>
                    </world>
                </instance>
                <instance type="marcaVaga1" uid="2980">
                    <properties>
                        <initial-visibility>Visible</initial-visibility>
                        <hotspot>Top-left</hotspot>
                    </properties>
                    <blend-mode>0</blend-mode>
                    <effect-fallback>0</effect-fallback>
                    <world>
                        <x>-0.011260986</x>
                        <y>400.789642334</y>
                        <z>0</z>
                        <width>426.502288818</width>
                        <height>6</height>
                        <depth>0</depth>
                        <hotspotX>0</hotspotX>
                        <hotspotY>0</hotspotY>
                        <angle>-1.57079649</angle>
                        <opacity>1</opacity>
                    </world>
                </instance>
                <instance type="marcaVaga1" uid="2981">
                    <properties>
                        <initial-visibility>Visible</initial-visibility>
                        <hotspot>Top-left</hotspot>
                    </properties>
                    <blend-mode>0</blend-mode>
                    <effect-fallback>0</effect-fallback>
                    <world>
                        <x>752.156555176</x>
                        <y>107.815383911</y>
                        <z>0</z>
                        <width>6</width>
                        <height>65.340759277</height>
                        <depth>0</depth>
                        <hotspotX>0</hotspotX>
                        <hotspotY>0</hotspotY>
                        <angle>-2.279452324</angle>
                        <opacity>1</opacity>
                    </world>
                </instance>
                <instance type="marcaVaga1" uid="2982">
                    <properties>
                        <initial-visibility>Visible</initial-visibility>
                        <hotspot>Top-left</hotspot>
                    </properties>
                    <blend-mode>0</blend-mode>
                    <effect-fallback>0</effect-fallback>
                    <world>
                        <x>751.500793457</x>
                        <y>171.770507813</y>
                        <z>0</z>
                        <width>6</width>
                        <height>65.340759277</height>
                        <depth>0</depth>
                        <hotspotX>0</hotspotX>
                        <hotspotY>0</hotspotY>
                        <angle>-2.279452324</angle>
                        <opacity>1</opacity>
                    </world>
                </instance>
                <instance type="marcaVaga1" uid="2983">
                    <properties>
                        <initial-visibility>Visible</initial-visibility>
                        <hotspot>Top-left</hotspot>
                    </properties>
                    <blend-mode>0</blend-mode>
                    <effect-fallback>0</effect-fallback>
                    <world>
                        <x>751.498962402</x>
                        <y>234.483810425</y>
                        <z>0</z>
                        <width>6</width>
                        <height>65.340759277</height>
                        <depth>0</depth>
                        <hotspotX>0</hotspotX>
                        <hotspotY>0</hotspotY>
                        <angle>-2.279452324</angle>
                        <opacity>1</opacity>
                    </world>
                </instance>
                <instance type="marcaVaga1" uid="2984">
                    <properties>
                        <initial-visibility>Visible</initial-visibility>
                        <hotspot>Top-left</hotspot>
                    </properties>
                    <blend-mode>0</blend-mode>
                    <effect-fallback>0</effect-fallback>
                    <world>
                        <x>750.260314941</x>
                        <y>300.301818848</y>
                        <z>0</z>
                        <width>6</width>
                        <height>65.340759277</height>
                        <depth>0</depth>
                        <hotspotX>0</hotspotX>
                        <hotspotY>0</hotspotY>
                        <angle>-2.279452324</angle>
                        <opacity>1</opacity>
                    </world>
                </instance>
                <instance type="marcaVaga1" uid="2985">
                    <properties>
                        <initial-visibility>Visible</initial-visibility>
                        <hotspot>Top-left</hotspot>
                    </properties>
                    <blend-mode>0</blend-mode>
                    <effect-fallback>0</effect-fallback>
                    <world>
                        <x>752.743225098</x>
                        <y>362.393463135</y>
                        <z>0</z>
                        <width>6</width>
                        <height>65.340759277</height>
                        <depth>0</depth>
                        <hotspotX>0</hotspotX>
                        <hotspotY>0</hotspotY>
                        <angle>-2.279452324</angle>
                        <opacity>1</opacity>
                    </world>
                </instance>
                <instance type="marcaVaga1" uid="2986">
                    <properties>
                        <initial-visibility>Visible</initial-visibility>
                        <hotspot>Top-left</hotspot>
                    </properties>
                    <blend-mode>0</blend-mode>
                    <effect-fallback>0</effect-fallback>
                    <world>
                        <x>757.637512207</x>
                        <y>435.370361328</y>
                        <z>0</z>
                        <width>15.429209709</width>
                        <height>65.340759277</height>
                        <depth>0</depth>
                        <hotspotX>0</hotspotX>
                        <hotspotY>0</hotspotY>
                        <angle>-2.279452324</angle>
                        <opacity>1</opacity>
                    </world>
                </instance>
                <instance type="carroEstacionado10" uid="2999">
                    <properties>
                        <initial-visibility>Visible</initial-visibility>
                        <initial-animation>Default</initial-animation>
                        <initial-frame>0</initial-frame>
                        <collisions>Enabled</collisions>
                    </properties>
                    <behavior-instances>
                        <behavior-instance type="Solid">
                            <properties>
                                <initial-state>Enabled</initial-state>
                            </properties>
                        </behavior-instance>
                    </behavior-instances>
                    <blend-mode>0</blend-mode>
                    <effect-fallback>0</effect-fallback>
                    <world>
                        <x>46.826309204</x>
                        <y>132.756347656</y>
                        <z>0</z>
                        <width>25</width>
                        <height>42</height>
                        <depth>0</depth>
                        <hotspotX>0.720149279</hotspotX>
                        <hotspotY>0.985037386</hotspotY>
                        <angle>-0.785398483</angle>
                        <opacity>1</opacity>
                    </world>
                </instance>
                <instance type="marcaVaga1" uid="3000">
                    <properties>
                        <initial-visibility>Visible</initial-visibility>
                        <hotspot>Top-left</hotspot>
                    </properties>
                    <blend-mode>0</blend-mode>
                    <effect-fallback>0</effect-fallback>
                    <world>
                        <x>0.99559021</x>
                        <y>67.392417908</y>
                        <z>0</z>
                        <width>6</width>
                        <height>65</height>
                        <depth>0</depth>
                        <hotspotX>0</hotspotX>
                        <hotspotY>0</hotspotY>
                        <angle>-0.763955951</angle>
                        <opacity>1</opacity>
                    </world>
                </instance>
                <instance type="marcaVaga1" uid="3001">
                    <properties>
                        <initial-visibility>Visible</initial-visibility>
                        <hotspot>Top-left</hotspot>
                    </properties>
                    <blend-mode>0</blend-mode>
                    <effect-fallback>0</effect-fallback>
                    <world>
                        <x>-0.219032288</x>
                        <y>131.254776001</y>
                        <z>0</z>
                        <width>6</width>
                        <height>65</height>
                        <depth>0</depth>
                        <hotspotX>0</hotspotX>
                        <hotspotY>0</hotspotY>
                        <angle>-0.763955951</angle>
                        <opacity>1</opacity>
                    </world>
                </instance>
                <instance type="marcaVaga1" uid="3002">
                    <properties>
                        <initial-visibility>Visible</initial-visibility>
                        <hotspot>Top-left</hotspot>
                    </properties>
                    <blend-mode>0</blend-mode>
                    <effect-fallback>0</effect-fallback>
                    <world>
                        <x>1.283401489</x>
                        <y>195.866500854</y>
                        <z>0</z>
                        <width>6</width>
                        <height>65</height>
                        <depth>0</depth>
                        <hotspotX>0</hotspotX>
                        <hotspotY>0</hotspotY>
                        <angle>-0.763955951</angle>
                        <opacity>1</opacity>
                    </world>
                </instance>
                <instance type="marcaVaga1" uid="3003">
                    <properties>
                        <initial-visibility>Visible</initial-visibility>
                        <hotspot>Top-left</hotspot>
                    </properties>
                    <blend-mode>0</blend-mode>
                    <effect-fallback>0</effect-fallback>
                    <world>
                        <x>2.035060883</x>
                        <y>259.728820801</y>
                        <z>0</z>
                        <width>6</width>
                        <height>65</height>
                        <depth>0</depth>
                        <hotspotX>0</hotspotX>
                        <hotspotY>0</hotspotY>
                        <angle>-0.763955951</angle>
                        <opacity>1</opacity>
                    </world>
                </instance>
                <instance type="marcaVaga1" uid="3004">
                    <properties>
                        <initial-visibility>Visible</initial-visibility>
                        <hotspot>Top-left</hotspot>
                    </properties>
                    <blend-mode>0</blend-mode>
                    <effect-fallback>0</effect-fallback>
                    <world>
                        <x>2.035060883</x>
                        <y>322.839538574</y>
                        <z>0</z>
                        <width>6</width>
                        <height>65</height>
                        <depth>0</depth>
                        <hotspotX>0</hotspotX>
                        <hotspotY>0</hotspotY>
                        <angle>-0.763955951</angle>
                        <opacity>1</opacity>
                    </world>
                </instance>
                <instance type="marcaVaga1" uid="3005">
                    <properties>
                        <initial-visibility>Visible</initial-visibility>
                        <hotspot>Top-left</hotspot>
                    </properties>
                    <blend-mode>0</blend-mode>
                    <effect-fallback>0</effect-fallback>
                    <world>
                        <x>-3.400836945</x>
                        <y>391.908325195</y>
                        <z>0</z>
                        <width>13.527856827</width>
                        <height>65</height>
                        <depth>0</depth>
                        <hotspotX>0</hotspotX>
                        <hotspotY>0</hotspotY>
                        <angle>-0.763955951</angle>
                        <opacity>1</opacity>
                    </world>
                </instance>
                <instance type="carroEstacionado11" uid="3006">
                    <properties>
                        <initial-visibility>Visible</initial-visibility>
                        <initial-animation>Default</initial-animation>
                        <initial-frame>0</initial-frame>
                        <collisions>Enabled</collisions>
                    </properties>
                    <behavior-instances>
                        <behavior-instance type="Solid">
                            <properties>
                                <initial-state>Enabled</initial-state>
                            </properties>
                        </behavior-instance>
                    </behavior-instances>
                    <blend-mode>0</blend-mode>
                    <effect-fallback>0</effect-fallback>
                    <world>
                        <x>45.460090637</x>
                        <y>196.619277954</y>
                        <z>0</z>
                        <width>25</width>
                        <height>42</height>
                        <depth>0</depth>
                        <hotspotX>0.720149279</hotspotX>
                        <hotspotY>0.985037386</hotspotY>
                        <angle>-0.785398483</angle>
                        <opacity>1</opacity>
                    </world>
                </instance>
                <instance type="carroEstacionado12" uid="3007">
                    <properties>
                        <initial-visibility>Visible</initial-visibility>
                        <initial-animation>Default</initial-animation>
                        <initial-frame>0</initial-frame>
                        <collisions>Enabled</collisions>
                    </properties>
                    <behavior-instances>
                        <behavior-instance type="Solid">
                            <properties>
                                <initial-state>Enabled</initial-state>
                            </properties>
                        </behavior-instance>
                    </behavior-instances>
                    <blend-mode>0</blend-mode>
                    <effect-fallback>0</effect-fallback>
                    <world>
                        <x>29.682266235</x>
                        <y>252.966842651</y>
                        <z>0</z>
                        <width>25</width>
                        <height>42</height>
                        <depth>0</depth>
                        <hotspotX>0.485074639</hotspotX>
                        <hotspotY>0.591022432</hotspotY>
                        <angle>-0.785398483</angle>
                        <opacity>1</opacity>
                    </world>
                </instance>
                <instance type="carroEstacionado13" uid="3008">
                    <properties>
                        <initial-visibility>Visible</initial-visibility>
                        <initial-animation>Default</initial-animation>
                        <initial-frame>0</initial-frame>
                        <collisions>Enabled</collisions>
                    </properties>
                    <behavior-instances>
                        <behavior-instance type="Solid">
                            <properties>
                                <initial-state>Enabled</initial-state>
                            </properties>
                        </behavior-instance>
                    </behavior-instances>
                    <blend-mode>0</blend-mode>
                    <effect-fallback>0</effect-fallback>
                    <world>
                        <x>30.433349609</x>
                        <y>316.077514648</y>
                        <z>0</z>
                        <width>25</width>
                        <height>42</height>
                        <depth>0</depth>
                        <hotspotX>0.481343269</hotspotX>
                        <hotspotY>0.586034894</hotspotY>
                        <angle>-0.785398483</angle>
                        <opacity>1</opacity>
                    </world>
                </instance>
                <instance type="carroEstacionado14" uid="3009">
                    <properties>
                        <initial-visibility>Visible</initial-visibility>
                        <initial-animation>Default</initial-animation>
                        <initial-frame>0</initial-frame>
                        <collisions>Enabled</collisions>
                    </properties>
                    <behavior-instances>
                        <behavior-instance type="Solid">
                            <properties>
                                <initial-state>Enabled</initial-state>
                            </properties>
                        </behavior-instance>
                    </behavior-instances>
                    <blend-mode>0</blend-mode>
                    <effect-fallback>0</effect-fallback>
                    <world>
                        <x>25.1746521</x>
                        <y>374.68057251</y>
                        <z>0</z>
                        <width>25</width>
                        <height>42</height>
                        <depth>0</depth>
                        <hotspotX>0.51119405</hotspotX>
                        <hotspotY>0.436408967</hotspotY>
                        <angle>-0.785398483</angle>
                        <opacity>1</opacity>
                    </world>
                </instance>
                <instance type="carroEstacionado10" uid="3011">
                    <properties>
                        <initial-visibility>Visible</initial-visibility>
                        <initial-animation>Default</initial-animation>
                        <initial-frame>0</initial-frame>
                        <collisions>Enabled</collisions>
                    </properties>
                    <behavior-instances>
                        <behavior-instance type="Solid">
                            <properties>
                                <initial-state>Enabled</initial-state>
                            </properties>
                        </behavior-instance>
                    </behavior-instances>
                    <blend-mode>0</blend-mode>
                    <effect-fallback>0</effect-fallback>
                    <world>
                        <x>760.114257813</x>
                        <y>136.51348877</y>
                        <z>0</z>
                        <width>25</width>
                        <height>42</height>
                        <depth>0</depth>
                        <hotspotX>0.720149279</hotspotX>
                        <hotspotY>0.985037386</hotspotY>
                        <angle>0.802851439</angle>
                        <opacity>1</opacity>
                    </world>
                </instance>
                <instance type="carroEstacionado11" uid="3012">
                    <properties>
                        <initial-visibility>Visible</initial-visibility>
                        <initial-animation>Default</initial-animation>
                        <initial-frame>0</initial-frame>
                        <collisions>Enabled</collisions>
                    </properties>
                    <behavior-instances>
                        <behavior-instance type="Solid">
                            <properties>
                                <initial-state>Enabled</initial-state>
                            </properties>
                        </behavior-instance>
                    </behavior-instances>
                    <blend-mode>0</blend-mode>
                    <effect-fallback>0</effect-fallback>
                    <world>
                        <x>760.433837891</x>
                        <y>200.61706543</y>
                        <z>0</z>
                        <width>25</width>
                        <height>42</height>
                        <depth>0</depth>
                        <hotspotX>0.720149279</hotspotX>
                        <hotspotY>0.985037386</hotspotY>
                        <angle>0.802851439</angle>
                        <opacity>1</opacity>
                    </world>
                </instance>
                <instance type="carroEstacionado12" uid="3013">
                    <properties>
                        <initial-visibility>Visible</initial-visibility>
                        <initial-animation>Default</initial-animation>
                        <initial-frame>0</initial-frame>
                        <collisions>Enabled</collisions>
                    </properties>
                    <behavior-instances>
                        <behavior-instance type="Solid">
                            <properties>
                                <initial-state>Enabled</initial-state>
                            </properties>
                        </behavior-instance>
                    </behavior-instances>
                    <blend-mode>0</blend-mode>
                    <effect-fallback>0</effect-fallback>
                    <world>
                        <x>768.789428711</x>
                        <y>246.410568237</y>
                        <z>0</z>
                        <width>25</width>
                        <height>42</height>
                        <depth>0</depth>
                        <hotspotX>0.485074639</hotspotX>
                        <hotspotY>0.591022432</hotspotY>
                        <angle>0.802851439</angle>
                        <opacity>1</opacity>
                    </world>
                </instance>
                <instance type="carroEstacionado13" uid="3014">
                    <properties>
                        <initial-visibility>Visible</initial-visibility>
                        <initial-animation>Default</initial-animation>
                        <initial-frame>0</initial-frame>
                        <collisions>Enabled</collisions>
                    </properties>
                    <behavior-instances>
                        <behavior-instance type="Solid">
                            <properties>
                                <initial-state>Enabled</initial-state>
                            </properties>
                        </behavior-instance>
                    </behavior-instances>
                    <blend-mode>0</blend-mode>
                    <effect-fallback>0</effect-fallback>
                    <world>
                        <x>766.756713867</x>
                        <y>313.035705566</y>
                        <z>0</z>
                        <width>25</width>
                        <height>42</height>
                        <depth>0</depth>
                        <hotspotX>0.481343269</hotspotX>
                        <hotspotY>0.586034894</hotspotY>
                        <angle>0.802851439</angle>
                        <opacity>1</opacity>
                    </world>
                </instance>
                <instance type="carroEstacionado14" uid="3015">
                    <properties>
                        <initial-visibility>Visible</initial-visibility>
                        <initial-animation>Default</initial-animation>
                        <initial-frame>0</initial-frame>
                        <collisions>Enabled</collisions>
                    </properties>
                    <behavior-instances>
                        <behavior-instance type="Solid">
                            <properties>
                                <initial-state>Enabled</initial-state>
                            </properties>
                        </behavior-instance>
                    </behavior-instances>
                    <blend-mode>0</blend-mode>
                    <effect-fallback>0</effect-fallback>
                    <world>
                        <x>777.323852539</x>
                        <y>368.644989014</y>
                        <z>0</z>
                        <width>25</width>
                        <height>42</height>
                        <depth>0</depth>
                        <hotspotX>0.51119405</hotspotX>
                        <hotspotY>0.436408967</hotspotY>
                        <angle>0.802851439</angle>
                        <opacity>1</opacity>
                    </world>
                </instance>
                <instance type="marcaVaga1" uid="2987">
                    <properties>
                        <initial-visibility>Visible</initial-visibility>
                        <hotspot>Top-left</hotspot>
                    </properties>
                    <blend-mode>0</blend-mode>
                    <effect-fallback>0</effect-fallback>
                    <world>
                        <x>2.274032593</x>
                        <y>7.731063843</y>
                        <z>0</z>
                        <width>6</width>
                        <height>65</height>
                        <depth>0</depth>
                        <hotspotX>0</hotspotX>
                        <hotspotY>0</hotspotY>
                        <angle>-0.763955951</angle>
                        <opacity>1</opacity>
                    </world>
                </instance>
                <instance type="carroEstacionado10" uid="2988">
                    <properties>
                        <initial-visibility>Visible</initial-visibility>
                        <initial-animation>Default</initial-animation>
                        <initial-frame>0</initial-frame>
                        <collisions>Enabled</collisions>
                    </properties>
                    <behavior-instances>
                        <behavior-instance type="Solid">
                            <properties>
                                <initial-state>Enabled</initial-state>
                            </properties>
                        </behavior-instance>
                    </behavior-instances>
                    <blend-mode>0</blend-mode>
                    <effect-fallback>0</effect-fallback>
                    <world>
                        <x>48.718757629</x>
                        <y>74.666320801</y>
                        <z>0</z>
                        <width>25</width>
                        <height>42</height>
                        <depth>0</depth>
                        <hotspotX>0.720149279</hotspotX>
                        <hotspotY>0.985037386</hotspotY>
                        <angle>-0.785398483</angle>
                        <opacity>1</opacity>
                    </world>
                </instance>
                <instance type="carroEstacionado10" uid="2940">
                    <properties>
                        <initial-visibility>Visible</initial-visibility>
                        <initial-animation>Default</initial-animation>
                        <initial-frame>0</initial-frame>
                        <collisions>Enabled</collisions>
                    </properties>
                    <behavior-instances>
                        <behavior-instance type="Solid">
                            <properties>
                                <initial-state>Enabled</initial-state>
                            </properties>
                        </behavior-instance>
                    </behavior-instances>
                    <blend-mode>0</blend-mode>
                    <effect-fallback>0</effect-fallback>
                    <world>
                        <x>60.33001709</x>
                        <y>20.708572388</y>
                        <z>0</z>
                        <width>25</width>
                        <height>42</height>
                        <depth>0</depth>
                        <hotspotX>0.720149279</hotspotX>
                        <hotspotY>0.985037386</hotspotY>
                        <angle>-0.785398483</angle>
                        <opacity>1</opacity>
                    </world>
                </instance>
                <instance type="marcaVaga1" uid="2989">
                    <properties>
                        <initial-visibility>Visible</initial-visibility>
                        <hotspot>Top-left</hotspot>
                    </properties>
                    <blend-mode>0</blend-mode>
                    <effect-fallback>0</effect-fallback>
                    <world>
                        <x>750.985107422</x>
                        <y>46.663299561</y>
                        <z>0</z>
                        <width>6</width>
                        <height>65.340759277</height>
                        <depth>0</depth>
                        <hotspotX>0</hotspotX>
                        <hotspotY>0</hotspotY>
                        <angle>-2.279452324</angle>
                        <opacity>1</opacity>
                    </world>
                </instance>
                <instance type="carroEstacionado10" uid="2990">
                    <properties>
                        <initial-visibility>Visible</initial-visibility>
                        <initial-animation>Default</initial-animation>
                        <initial-frame>0</initial-frame>
                        <collisions>Enabled</collisions>
                    </properties>
                    <behavior-instances>
                        <behavior-instance type="Solid">
                            <properties>
                                <initial-state>Enabled</initial-state>
                            </properties>
                        </behavior-instance>
                    </behavior-instances>
                    <blend-mode>0</blend-mode>
                    <effect-fallback>0</effect-fallback>
                    <world>
                        <x>761.914001465</x>
                        <y>68.519676208</y>
                        <z>0</z>
                        <width>25</width>
                        <height>42</height>
                        <depth>0</depth>
                        <hotspotX>0.720149279</hotspotX>
                        <hotspotY>0.985037386</hotspotY>
                        <angle>0.802851439</angle>
                        <opacity>1</opacity>
                    </world>
                </instance>
                <instance type="carroEstacionado10" uid="2991">
                    <properties>
                        <initial-visibility>Visible</initial-visibility>
                        <initial-animation>Default</initial-animation>
                        <initial-frame>0</initial-frame>
                        <collisions>Enabled</collisions>
                    </properties>
                    <behavior-instances>
                        <behavior-instance type="Solid">
                            <properties>
                                <initial-state>Enabled</initial-state>
                            </properties>
                        </behavior-instance>
                    </behavior-instances>
                    <blend-mode>0</blend-mode>
                    <effect-fallback>0</effect-fallback>
                    <world>
                        <x>751.667358398</x>
                        <y>20.709091187</y>
                        <z>0</z>
                        <width>25</width>
                        <height>42</height>
                        <depth>0</depth>
                        <hotspotX>0.720149279</hotspotX>
                        <hotspotY>0.985037386</hotspotY>
                        <angle>0.802851439</angle>
                        <opacity>1</opacity>
                    </world>
                </instance>
            </instances>
            <effects>
                <effect-type name="GlowHorizontal">
                    <effect id="glowhorizontal" />
                    <effect-instance type="GlowHorizontal">
                        <parameters>
                            <intensity>0.1</intensity>
                        </parameters>
                    </effect-instance>
                </effect-type>
                <effect-type name="GlowVertical">
                    <effect id="glowvertical" />
                    <effect-instance type="GlowVertical">
                        <parameters>
                            <intensity>0.1</intensity>
                        </parameters>
                    </effect-instance>
                </effect-type>
            </effects>
        </layer>
        <layer name="Layer 1" sid="709809701457536">
            <initially-visible>1</initially-visible>
            <background-color>255,255,255</background-color>
            <transparent>1</transparent>
            <parallax>
                <x>1</x>
                <y>1</y>
            </parallax>
            <zoom-rate>1</zoom-rate>
            <opacity>1</opacity>
            <force-own-texture>0</force-own-texture>
            <global>0</global>
            <use-render-cells>0</use-render-cells>
            <blend-mode>0</blend-mode>
            <effect-fallback>0</effect-fallback>
            <instances>
                <instance type="carro" uid="3026">
                    <properties>
                        <initial-visibility>Visible</initial-visibility>
                        <initial-animation>Default</initial-animation>
                        <initial-frame>0</initial-frame>
                        <collisions>Enabled</collisions>
                    </properties>
                    <behavior-instances>
                        <behavior-instance type="Car">
                            <properties>
                                <max-speed>350</max-speed>
                                <acceleration>200</acceleration>
                                <deceleration>300</deceleration>
                                <steer-speed>225</steer-speed>
                                <drift-recover>185</drift-recover>
                                <friction>0.4</friction>
                                <set-angle>Yes</set-angle>
                                <default-controls>No</default-controls>
                                <initial-state>Enabled</initial-state>
                            </properties>
                        </behavior-instance>
                        <behavior-instance type="BoundToLayout">
                            <properties>
                                <bound-by>Edge</bound-by>
                            </properties>
                        </behavior-instance>
                        <behavior-instance type="ScrollTo">
                            <properties>
                                <initial-state>Enabled</initial-state>
                            </properties>
                        </behavior-instance>
                    </behavior-instances>
                    <blend-mode>0</blend-mode>
                    <effect-fallback>0</effect-fallback>
                    <world>
                        <x>396.861053467</x>
                        <y>143</y>
                        <z>0</z>
                        <width>52</width>
                        <height>34</height>
                        <depth>0</depth>
                        <hotspotX>0.439635545</hotspotX>
                        <hotspotY>-0.003731343</hotspotY>
                        <angle>0</angle>
                        <opacity>1</opacity>
                    </world>
                </instance>
            </instances>
            <effects />
        </layer>
        <layer name="Layer 2" sid="717032814584463">
            <initially-visible>1</initially-visible>
            <background-color>255,255,255</background-color>
            <transparent>1</transparent>
            <parallax>
                <x>1</x>
                <y>1</y>
            </parallax>
            <zoom-rate>1</zoom-rate>
            <opacity>0.4</opacity>
            <force-own-texture>0</force-own-texture>
            <global>0</global>
            <use-render-cells>0</use-render-cells>
            <blend-mode>0</blend-mode>
            <effect-fallback>0</effect-fallback>
            <instances>
                <instance type="preto" uid="2996">
                    <properties>
                        <initial-visibility>Visible</initial-visibility>
                        <hotspot>Top-left</hotspot>
                    </properties>
                    <blend-mode>0</blend-mode>
                    <effect-fallback>0</effect-fallback>
                    <world>
                        <x>-13</x>
                        <y>-63</y>
                        <z>0</z>
                        <width>837</width>
                        <height>512</height>
                        <depth>0</depth>
                        <hotspotX>0</hotspotX>
                        <hotspotY>0</hotspotY>
                        <angle>0</angle>
                        <opacity>1</opacity>
                    </world>
                </instance>
            </instances>
            <effects />
        </layer>
        <layer name="Layer 3" sid="748181060923679">
            <initially-visible>1</initially-visible>
            <background-color>255,255,255</background-color>
            <transparent>1</transparent>
            <parallax>
                <x>1</x>
                <y>1</y>
            </parallax>
            <zoom-rate>1</zoom-rate>
            <opacity>1</opacity>
            <force-own-texture>0</force-own-texture>
            <global>0</global>
            <use-render-cells>0</use-render-cells>
            <blend-mode>0</blend-mode>
            <effect-fallback>0</effect-fallback>
            <instances>
                <instance type="BotaoJogar" uid="1935">
                    <properties>
                        <initial-visibility>Visible</initial-visibility>
                        <initial-animation>Default</initial-animation>
                        <initial-frame>0</initial-frame>
                        <collisions>Enabled</collisions>
                    </properties>
                    <blend-mode>0</blend-mode>
                    <effect-fallback>0</effect-fallback>
                    <world>
                        <x>171</x>
                        <y>212</y>
                        <z>0</z>
                        <width>96</width>
                        <height>48</height>
                        <depth>0</depth>
                        <hotspotX>0.510416687</hotspotX>
                        <hotspotY>0.458333343</hotspotY>
                        <angle>0</angle>
                        <opacity>1</opacity>
                    </world>
                </instance>
                <instance type="BotaoOpcoes" uid="2058">
                    <properties>
                        <initial-visibility>Visible</initial-visibility>
                        <initial-animation>Default</initial-animation>
                        <initial-frame>0</initial-frame>
                        <collisions>Enabled</collisions>
                    </properties>
                    <blend-mode>0</blend-mode>
                    <effect-fallback>0</effect-fallback>
                    <world>
                        <x>280</x>
                        <y>288</y>
                        <z>0</z>
                        <width>115</width>
                        <height>48</height>
                        <depth>0</depth>
                        <hotspotX>0.530434787</hotspotX>
                        <hotspotY>0.458333343</hotspotY>
                        <angle>0</angle>
                        <opacity>1</opacity>
                    </world>
                </instance>
                <instance type="BotaoSair" uid="2059">
                    <properties>
                        <initial-visibility>Visible</initial-visibility>
                        <initial-animation>Default</initial-animation>
                        <initial-frame>0</initial-frame>
                        <collisions>Enabled</collisions>
                    </properties>
                    <blend-mode>0</blend-mode>
                    <effect-fallback>0</effect-fallback>
                    <world>
                        <x>406</x>
                        <y>368</y>
                        <z>0</z>
                        <width>66</width>
                        <height>41</height>
                        <depth>0</depth>
                        <hotspotX>0.575757563</hotspotX>
                        <hotspotY>0.48780489</hotspotY>
                        <angle>0</angle>
                        <opacity>1</opacity>
                    </world>
                </instance>
                <instance type="BotaoLoja" uid="2060">
                    <properties>
                        <initial-visibility>Visible</initial-visibility>
                        <initial-animation>Default</initial-animation>
                        <initial-frame>0</initial-frame>
                        <collisions>Enabled</collisions>
                    </properties>
                    <blend-mode>0</blend-mode>
                    <effect-fallback>0</effect-fallback>
                    <world>
                        <x>663</x>
                        <y>319</y>
                        <z>0</z>
                        <width>76</width>
                        <height>46</height>
                        <depth>0</depth>
                        <hotspotX>0.5</hotspotX>
                        <hotspotY>0.434782594</hotspotY>
                        <angle>0</angle>
                        <opacity>1</opacity>
                    </world>
                </instance>
                <instance type="Titulo2" uid="633">
                    <properties>
                        <initial-visibility>Visible</initial-visibility>
                        <initial-animation>Default</initial-animation>
                        <initial-frame>0</initial-frame>
                        <collisions>Enabled</collisions>
                    </properties>
                    <blend-mode>0</blend-mode>
                    <effect-fallback>0</effect-fallback>
                    <world>
                        <x>401</x>
                        <y>72</y>
                        <z>0</z>
                        <width>885</width>
                        <height>452</height>
                        <depth>0</depth>
                        <hotspotX>0.500745177</hotspotX>
                        <hotspotY>0.501392782</hotspotY>
                        <angle>0</angle>
                        <opacity>1</opacity>
                    </world>
                </instance>
            </instances>
            <effects>
                <effect-type name="GlowHorizontal">
                    <effect id="glowhorizontal" />
                    <effect-instance type="GlowHorizontal">
                        <parameters>
                            <intensity>0.5</intensity>
                        </parameters>
                    </effect-instance>
                </effect-type>
                <effect-type name="GlowVertical">
                    <effect id="glowvertical" />
                    <effect-instance type="GlowVertical">
                        <parameters>
                            <intensity>0.5</intensity>
                        </parameters>
                    </effect-instance>
                </effect-type>
            </effects>
        </layer>
    </layers>
    <nonworld-instances />
    <effects />
</c2layout>
