<?xml version="1.0" encoding="utf-8" ?>
<c2eventsheet>
    <!--All the 'name' attributes are ignored by Construct 2 - they are there for readability only.-->
    <name>Eventos Cap2 Fase4</name>
    <events>
        <include>Eventos Pontos</include>
        <include>Eventos Carros</include>
        <event-block sid="611319172336210">
            <conditions>
                <condition id="-2" name="On start of layout" sid="341478577051854" type="System" />
            </conditions>
            <actions />
        </event-block>
    </events>
</c2eventsheet>
